mqa/__init__.py
mqa/flash_attn_triton.py
mqa/main.py
mqa-0.1.0.dist-info/LICENSE
mqa-0.1.0.dist-info/WHEEL
mqa-0.1.0.dist-info/METADATA
mqa-0.1.0.dist-info/RECORD
